renishawWiRE/__init__.py
renishawWiRE/export.py
renishawWiRE/types.py
renishawWiRE/utils.py
renishawWiRE/wdfReader.py
renishawWiRE-0.1.16.dist-info/LICENSE
renishawWiRE-0.1.16.dist-info/METADATA
renishawWiRE-0.1.16.dist-info/WHEEL
renishawWiRE-0.1.16.dist-info/entry_points.txt
renishawWiRE-0.1.16.dist-info/top_level.txt
renishawWiRE-0.1.16.dist-info/RECORD
