Metadata-Version: 2.1
Name: renishawWiRE
Version: 0.1.16
Summary: Reading wdf Raman spectroscopy file from Renishaw WiRE
Home-page: https://github.com/alchem0x2A/py-wdf-reader
Author: alchem0x2A
Author-email: alchem0x2a@gmail.com
License: MIT
Classifier: Programming Language :: Python
Classifier: Programming Language :: Python :: 3 :: Only
Classifier: Programming Language :: Python :: 3.6
Classifier: Programming Language :: Python :: 3.7
Classifier: Programming Language :: Python :: 3.8
Classifier: Programming Language :: Python :: 3.9
Classifier: Programming Language :: Python :: 3.10
Requires-Python: >=3.6
Provides-Extra: image
Provides-Extra: plot
License-File: LICENSE
